hercai/__init__.py
hercai/hercai.py
hercai-3.3.0.dist-info/LICENSE.md
hercai-3.3.0.dist-info/METADATA
hercai-3.3.0.dist-info/WHEEL
hercai-3.3.0.dist-info/top_level.txt
hercai-3.3.0.dist-info/RECORD
