Metadata-Version: 2.1
Name: hercai
Version: 3.3.0
Summary: A powerful Python Package for interacting with the Herc.ai API.
Home-page: https://github.com/Bes-js/Hercai.py
Author: fivesobes
License: GPL-3.0
Keywords: ai,chatbot,chatgpt,gpt,API,web,arc,smart,smartestchatbot,api,dalle,dall-e,text2image,texttoimage,text2img,texttoimg,image,image-generator,midjourney,diffusion,dall-e2,ai-images,ai-images-generator,gpt,discord,chat,chatbot,chatgpt4,chatgpt-4,openai,open-ai,hercai,herc,herc.ai,smartest,bot,robot,axios,canvafy,streamed-chatgpt-api,dart-openai-sdk,completions,cli,bin,command,console,cmd,bing,bing-chat,openaiapi,open.ai,openai-api,luppux,fivesobes,gemini,gemini-api,gemini-pro,google,five,be
Platform: UNKNOWN
Classifier: Development Status :: 5 - Production/Stable
Classifier: License :: OSI Approved :: MIT License
Classifier: Operating System :: OS Independent
Classifier: Programming Language :: Python :: 3
Classifier: Programming Language :: Python :: 3 :: Only
Classifier: Programming Language :: Python :: 3.6
Classifier: Programming Language :: Python :: 3.7
Classifier: Programming Language :: Python :: 3.8
Classifier: Programming Language :: Python :: 3.9
Classifier: Programming Language :: Python :: 3.10
Classifier: Programming Language :: Python :: 3.11
Classifier: Programming Language :: Python :: 3.12
Classifier: Programming Language :: Python :: Implementation :: CPython
Classifier: Topic :: Internet :: WWW/HTTP :: Indexing/Search
Classifier: Topic :: Software Development :: Libraries :: Python Modules
Requires: requests
License-File: LICENSE.md
Requires-Dist: requests
